LICENSE
MANIFEST.in
README.rst
r.html
setup.py
dist/django-livevalidation-0.1.1.tar.gz
django_livevalidation.egg-info/PKG-INFO
django_livevalidation.egg-info/SOURCES.txt
django_livevalidation.egg-info/dependency_links.txt
django_livevalidation.egg-info/top_level.txt
example_project/__init__.py
example_project/dev.db
example_project/manage.py
example_project/media
example_project/settings.py
example_project/urls.py
example_project/templates/test.html
livevalidation/__init__.py
livevalidation/models.py
livevalidation/settings.py
livevalidation/tests.py
livevalidation/validator.py
livevalidation/media/css/livevalidation.css
livevalidation/media/js/livevalidation_standalone.compressed.js
livevalidation/templates/admin/base_site.html
livevalidation/templates/admin/change_form.html
livevalidation/templates/admin/auth/user/add_form.html
livevalidation/templates/livevalidation/header.html
livevalidation/templatetags/__init__.py
livevalidation/templatetags/live_validation.py