Metadata-Version: 1.0
Name: django-livevalidation
Version: 0.1.1
Summary: Live validation for Django forms. It validates as you type. Uses scripts from livevalidation.com
Home-page: http://github.com/washingtontimes/django-livevalidation
Author: Justin Quick
Author-email: justquick@gmail.com
License: UNKNOWN
Platform: UNKNOWN
